framex/__init__.py
framex/cli.py
framex/config.py
framex/consts.py
framex/log.py
framex/utils.py
framex/adapter/__init__.py
framex/adapter/base.py
framex/adapter/local_adapyer.py
framex/adapter/ray_adapter.py
framex/driver/__init__.py
framex/driver/application.py
framex/driver/auth.py
framex/driver/decorator.py
framex/driver/ingress.py
framex/plugin/__init__.py
framex/plugin/base.py
framex/plugin/load.py
framex/plugin/manage.py
framex/plugin/model.py
framex/plugin/on.py
framex/plugins/__init__.py
framex/plugins/echo.py
framex/plugins/proxy/__init__.py
framex/plugins/proxy/builder.py
framex/plugins/proxy/config.py
framex/plugins/proxy/model.py
framex_kit-0.2.9.dist-info/METADATA
framex_kit-0.2.9.dist-info/WHEEL
framex_kit-0.2.9.dist-info/entry_points.txt
framex_kit-0.2.9.dist-info/licenses/LICENSE
framex_kit-0.2.9.dist-info/RECORD
