Metadata-Version: 2.4
Name: framex-kit
Version: 0.2.9
Summary: A lightweight plugin injection framework for Python.
Author-email: touale <touale@local.com>
License-File: LICENSE
Requires-Python: >=3.11
Requires-Dist: aiocache>=0.12.3
Requires-Dist: click>=8.1.8
Requires-Dist: fastapi<1.0,>=0.115.13
Requires-Dist: httpx>=0.28.1
Requires-Dist: loguru>=0.7.3
Requires-Dist: pydantic-settings>=2.10.1
Requires-Dist: pydantic>=2.11.7
Requires-Dist: pyjwt>=2.10.1
Requires-Dist: pytz>=2025.2
Requires-Dist: ray[serve]==2.53.0
Requires-Dist: sentry-sdk[fastapi]>=2.33.0
Requires-Dist: tomli>=2.2.1
Provides-Extra: release
Requires-Dist: poethepoet>=0.36.0; extra == 'release'
Requires-Dist: python-semantic-release>=10.2.0; extra == 'release'
